{
    "swagger": "2.0",
    "info": {
        "description": "This is a sample JWT authentication API.",
        "title": "JWT Auth API",
        "contact": {},
        "version": "1"
    },
    "host": "localhost:8080",
    "basePath": "/",
    "paths": {
        "/auth": {
            "get": {
                "security": [
                    {
                        "ApiKeyAuth": []
                    }
                ],
                "description": "Verify if the incoming request contains a valid JSON Web Token (JWT) in the \"Authorization\" header, extract the user ID from it, and set it in the context for subsequent requests to use.",
                "consumes": [
                    "application/json"
                ],
                "produces": [
                    "application/json"
                ],
                "tags": [
                    "Authentication"
                ],
                "summary": "Authenticate user using JWT",
                "parameters": [
                    {
                        "type": "string",
                        "description": "JWT Token with 'Bearer ' prefix",
                        "name": "Authorization",
                        "in": "header",
                        "required": true
                    }
                ],
                "responses": {
                    "200": {
                        "description": "OK",
                        "schema": {
                            "type": "string"
                        }
                    }
                }
            }
        },
        "/login": {
            "post": {
                "description": "Authenticate user with provided credentials and return JWT token",
                "consumes": [
                    "application/json"
                ],
                "produces": [
                    "application/json"
                ],
                "parameters": [
                    {
                        "description": "Login credentials",
                        "name": "input",
                        "in": "body",
                        "required": true,
                        "schema": {
                            "$ref": "#/definitions/models.LoginRequest"
                        }
                    }
                ],
                "responses": {
                    "200": {
                        "description": "JWT token",
                        "schema": {
                            "$ref": "#/definitions/models.LoginRequest"
                        }
                    },
                    "400": {
                        "description": "Invalid login credentials",
                        "schema": {
                            "type": "string"
                        }
                    },
                    "500": {
                        "description": "Server error",
                        "schema": {
                            "type": "string"
                        }
                    }
                }
            }
        },
        "/register": {
            "post": {
                "description": "Register a new user with the provided username and password",
                "consumes": [
                    "application/json"
                ],
                "produces": [
                    "application/json"
                ],
                "parameters": [
                    {
                        "description": "Registration details",
                        "name": "input",
                        "in": "body",
                        "required": true,
                        "schema": {
                            "$ref": "#/definitions/models.LoginRequest"
                        }
                    }
                ],
                "responses": {
                    "201": {
                        "description": "Successfully registered user",
                        "schema": {
                            "type": "string"
                        }
                    },
                    "400": {
                        "description": "Invalid registration details",
                        "schema": {
                            "type": "string"
                        }
                    },
                    "500": {
                        "description": "Server error",
                        "schema": {
                            "type": "string"
                        }
                    }
                }
            }
        },
        "/users/{id}": {
            "get": {
                "description": "Retrieve a user by ID",
                "produces": [
                    "application/json"
                ],
                "parameters": [
                    {
                        "type": "integer",
                        "description": "User ID",
                        "name": "id",
                        "in": "path",
                        "required": true
                    }
                ],
                "responses": {
                    "200": {
                        "description": "OK",
                        "schema": {
                            "$ref": "#/definitions/models.User"
                        }
                    },
                    "400": {
                        "description": "Bad Request",
                        "schema": {
                            "type": "string"
                        }
                    },
                    "404": {
                        "description": "User not found",
                        "schema": {
                            "type": "string"
                        }
                    }
                }
            }
        }
    },
    "definitions": {
        "models.LoginRequest": {
            "type": "object",
            "required": [
                "password",
                "username"
            ],
            "properties": {
                "password": {
                    "type": "string"
                },
                "username": {
                    "type": "string"
                }
            }
        },
        "models.User": {
            "type": "object",
            "properties": {
                "password": {
                    "type": "string"
                },
                "username": {
                    "description": "gorm.Model",
                    "type": "string"
                }
            }
        }
    }
}